{
    "name": "Score",
    "fields": [
        {
            "fieldName": "name",
            "fieldType": "String"
        }
    ],
    "relationships": [
        {
            "relationshipType": "one-to-many",
            "otherEntityName": "scorePart",
            "otherEntityRelationshipName": "score",
            "relationshipName": "scorePart"
        },
        {
            "relationshipType": "many-to-one",
            "otherEntityName": "song",
            "otherEntityRelationshipName": "score",
            "relationshipName": "song",
            "otherEntityField": "id"
        }
    ],
    "changelogDate": "20200214211100",
    "entityTableName": "score",
    "dto": "no",
    "pagination": "pagination",
    "service": "no",
    "jpaMetamodelFiltering": false,
    "fluentMethods": true,
    "readOnly": false,
    "clientRootFolder": "",
    "applications": "*"
}